Metadata-Version: 2.1
Name: Flask-REST-JSONAPI
Version: 0.31.2
Summary: Flask extension to create REST web api according to JSONAPI 1.0 specification with Flask, Marshmallow                  and data provider of your choice (SQLAlchemy, MongoDB, ...)
Home-page: https://github.com/miLibris/flask-rest-jsonapi
Author: miLibris API Team
Author-email: pf@milibris.net
License: MIT
Keywords: web api rest jsonapi flask sqlalchemy marshmallow
Platform: any
Classifier: Framework :: Flask
Classifier: Programming Language :: Python :: 3
Classifier: Programming Language :: Python :: 3.5
Classifier: Programming Language :: Python :: 3.6
Classifier: Programming Language :: Python :: 3.8
Classifier: License :: OSI Approved :: MIT License
Provides-Extra: docs
Provides-Extra: dev
